odoo/addons/project_status/README.rst
odoo/addons/project_status/__init__.py
odoo/addons/project_status/__manifest__.py
odoo/addons/project_status/data/data.xml
odoo/addons/project_status/i18n/de.po
odoo/addons/project_status/i18n/es.po
odoo/addons/project_status/i18n/es_AR.po
odoo/addons/project_status/i18n/fr.po
odoo/addons/project_status/i18n/fr_FR.po
odoo/addons/project_status/i18n/it.po
odoo/addons/project_status/i18n/project_status.pot
odoo/addons/project_status/i18n/sl.po
odoo/addons/project_status/migrations/13.0.2.0.0/post-migration.py
odoo/addons/project_status/models/__init__.py
odoo/addons/project_status/models/project.py
odoo/addons/project_status/models/project_status.py
odoo/addons/project_status/readme/CONTRIBUTORS.rst
odoo/addons/project_status/readme/DESCRIPTION.rst
odoo/addons/project_status/readme/USAGE.rst
odoo/addons/project_status/security/ir.model.access.csv
odoo/addons/project_status/security/project_status.xml
odoo/addons/project_status/static/description/icon.png
odoo/addons/project_status/static/description/index.html
odoo/addons/project_status/tests/__init__.py
odoo/addons/project_status/tests/test_status.py
odoo/addons/project_status/views/project.xml
odoo/addons/project_status/views/project_status.xml
odoo_addon_project_status-16.0.1.0.0.4.dist-info/METADATA
odoo_addon_project_status-16.0.1.0.0.4.dist-info/WHEEL
odoo_addon_project_status-16.0.1.0.0.4.dist-info/top_level.txt
odoo_addon_project_status-16.0.1.0.0.4.dist-info/RECORD
